hookpilot/__init__.py
hookpilot/cli.py
hookpilot/config.py
hookpilot/executor.py
hookpilot/git_hooks.py
hookpilot/utils.py
hookpilot-0.1.0.dist-info/entry_points.txt
hookpilot-0.1.0.dist-info/LICENSE
hookpilot-0.1.0.dist-info/METADATA
hookpilot-0.1.0.dist-info/WHEEL
hookpilot-0.1.0.dist-info/RECORD
