Metadata-Version: 2.3
Name: hookpilot
Version: 0.1.0
Summary: A lightweight Git Hook Manager in Python
License: MIT
Author: HUMBLEFOOL
Author-email: 123amitrana0123@gmail.com
Requires-Python: >=3.10
Classifier: License :: OSI Approved :: MIT License
Classifier: Programming Language :: Python :: 3
Classifier: Programming Language :: Python :: 3.10
Classifier: Programming Language :: Python :: 3.11
Classifier: Programming Language :: Python :: 3.12
Classifier: Programming Language :: Python :: 3.13
Requires-Dist: gitpython (>=3.1.42,<4.0.0)
Requires-Dist: pyyaml (>=6.0.1,<7.0.0)
Requires-Dist: typer (>=0.12.0,<1.0.0)
Project-URL: Homepage, https://github.com/HUMBLEFOOL/hookpilot
Project-URL: Issues, https://github.com/HUMBLEFOOL/hookpilot/issues
Project-URL: Repository, https://github.com/HUMBLEFOOL/hookpilot
